deployserver/__init__.py
deployserver-0.5.2.dist-info/LICENSE.txt
deployserver-0.5.2.dist-info/METADATA
deployserver-0.5.2.dist-info/WHEEL
deployserver-0.5.2.dist-info/top_level.txt
deployserver-0.5.2.dist-info/RECORD
