Metadata-Version: 2.1
Name: deployserver
Version: 0.5.2
Summary: Deploy your project automatically when git branch was updated.
Home-page: https://github.com/codex-team/deployserver
Author: CodeX Team
Author-email: team@ifmo.su
License: MIT
Keywords: automatically deploy git project
Platform: UNKNOWN
Classifier: Intended Audience :: Developers
Classifier: Topic :: Software Development :: Build Tools
Classifier: License :: OSI Approved :: MIT License
Classifier: Programming Language :: Python :: 3.5
Classifier: Environment :: Console
Requires-Python: >=3.5
Requires-Dist: aiohttp
Requires-Dist: asyncio
